zza/__init__.py
zza-0.0.0a0.dist-info/METADATA
zza-0.0.0a0.dist-info/WHEEL
zza-0.0.0a0.dist-info/licenses/LICENSE
zza-0.0.0a0.dist-info/RECORD
